sijuiacion_lang/__init__.py
sijuiacion_lang/blockaddr.py
sijuiacion_lang/bytecode_instrs.py
sijuiacion_lang/bytecode_patch.py
sijuiacion_lang/codegen.py
sijuiacion_lang/instr_names.py
sijuiacion_lang/interface.py
sijuiacion_lang/lowering.py
sijuiacion_lang/moshmosh_rts.py
sijuiacion_lang/parser.py
sijuiacion_lang/parser_wrap.py
sijuiacion_lang/preserved_registers.py
sijuiacion_lang/sijuiacion.py
sijuiacion_lang/support.py
test/__init__.py
test/codegen.py
test/dev.py
test/test_adts.py
test/test_dev.py
test/try_closures.py
test/try_indir.py
test/try_lower.py
test/try_parser.py
sijuiacion_lang-0.2.0.dist-info/LICENSE
sijuiacion_lang-0.2.0.dist-info/METADATA
sijuiacion_lang-0.2.0.dist-info/WHEEL
sijuiacion_lang-0.2.0.dist-info/entry_points.txt
sijuiacion_lang-0.2.0.dist-info/top_level.txt
sijuiacion_lang-0.2.0.dist-info/RECORD
