Metadata-Version: 2.1
Name: sijuiacion-lang
Version: 0.2.0
Summary: UNKNOWN
Home-page: https://github.com/RemuLang/sijuiacion-lang
Author: thautwarm
Author-email: twshere@outlook.com
License: mit
Platform: any
Classifier: Programming Language :: Python :: 3.7
Classifier: Programming Language :: Python :: Implementation :: CPython
Requires-Python: >=3.6.0
Requires-Dist: rbnf-rts
Requires-Dist: argser
Requires-Dist: typing-extensions
Requires-Dist: bytecode
